babelrts.py
babelrts-1.1.7.dist-info/METADATA
babelrts-1.1.7.dist-info/WHEEL
babelrts-1.1.7.dist-info/top_level.txt
babelrts-1.1.7.dist-info/RECORD
