Metadata-Version: 2.1
Name: babelrts
Version: 1.1.7
Summary: BastRTS is a tool to perform regression test selection. It is still under development.
Home-page: https://github.com/GabrieleMaurina/babelRTS
Author: Gabriele Maurina
Author-email: gabrielemaurina95@gmail.com
License: MIT
Platform: UNKNOWN
Classifier: Programming Language :: Python :: 3
Classifier: License :: OSI Approved :: MIT License
Classifier: Operating System :: OS Independent
Requires-Python: >=3.8
